pytwitter/__init__.py
pytwitter/api.py
pytwitter/error.py
pytwitter/models/__init__.py
pytwitter/models/base.py
pytwitter/models/compliance.py
pytwitter/models/dm_event.py
pytwitter/models/ext.py
pytwitter/models/list.py
pytwitter/models/media.py
pytwitter/models/media_upload.py
pytwitter/models/place.py
pytwitter/models/poll.py
pytwitter/models/space.py
pytwitter/models/stream.py
pytwitter/models/trend.py
pytwitter/models/tweet.py
pytwitter/models/usage.py
pytwitter/models/user.py
pytwitter/rate_limit.py
pytwitter/streaming.py
pytwitter/utils/__init__.py
pytwitter/utils/convertors.py
pytwitter/utils/validators.py
python_twitter_v2-0.9.1.dist-info/LICENSE
python_twitter_v2-0.9.1.dist-info/METADATA
python_twitter_v2-0.9.1.dist-info/WHEEL
python_twitter_v2-0.9.1.dist-info/RECORD
