Metadata-Version: 2.1
Name: python-twitter-v2
Version: 0.9.1
Summary: A simple Python wrapper for Twitter API v2 ✨ 🍰 ✨
Home-page: https://github.com/sns-sdks/python-twitter
License: MIT
Keywords: twitter,twitter sdk,twitter api,Twitter API V2
Author: ikaroskun
Author-email: merle.liukun@gmail.com
Requires-Python: >=3.7,<4.0
Classifier: Intended Audience :: Developers
Classifier: License :: OSI Approved :: MIT License
Classifier: Operating System :: OS Independent
Classifier: Programming Language :: Python :: 3
Classifier: Programming Language :: Python :: 3.7
Classifier: Programming Language :: Python :: 3.8
Classifier: Programming Language :: Python :: 3.9
Classifier: Programming Language :: Python :: 3.10
Classifier: Programming Language :: Python :: 3.11
Classifier: Programming Language :: Python :: 3.12
Classifier: Programming Language :: Python :: 3 :: Only
Classifier: Programming Language :: Python :: Implementation :: CPython
Classifier: Topic :: Software Development :: Libraries :: Python Modules
Requires-Dist: Authlib (>=1.0.0,<2.0.0)
Requires-Dist: dataclasses-json (>=0.5.7,<0.6.0)
Requires-Dist: requests (>=2.28,<3.0)
Project-URL: Repository, https://github.com/sns-sdks/python-twitter
